{"clients":[{"addresses":[],"bonus_balance":22.0,"created_at":1778146172567,"id":"CLIENT-78","last_order_date":1778146172698,"name":"Мичурина","notes":"","phone":"+79604608172","total_orders":1,"total_spent":440.0,"updated_at":1778146172698},{"addresses":[],"bonus_balance":33.0,"created_at":1778146126711,"id":"CLIENT-77","last_order_date":1778146126748,"name":"островок","notes":"","phone":"+79381248818","total_orders":1,"total_spent":660.0,"updated_at":1778146126748},{"addresses":[],"bonus_balance":44.0,"created_at":1778146036051,"id":"CLIENT-76","last_order_date":1778146036076,"name":"таймер","notes":"","phone":"+79287528676","total_orders":1,"total_spent":880.0,"updated_at":1778146036076},{"addresses":[],"bonus_balance":22.0,"created_at":1778143546493,"id":"CLIENT-75","last_order_date":1778146253821,"name":"ленина","notes":"","phone":"+79287752114","total_orders":2,"total_spent":440.0,"updated_at":1778146253821},{"addresses":[],"bonus_balance":23.0,"created_at":1778140794754,"id":"CLIENT-74","last_order_date":1778140794782,"name":"школа","notes":"","phone":"+79281192456","total_orders":1,"total_spent":460.0,"updated_at":1778140794782},{"addresses":[],"bonus_balance":14.0,"created_at":1778139306293,"id":"CLIENT-73","last_order_date":1778139306314,"name":"крымскогл","notes":"","phone":"+79281367068","total_orders":1,"total_spent":280.0,"updated_at":1778139306314},{"addresses":[],"bonus_balance":22.0,"created_at":1778139082457,"id":"CLIENT-72","last_order_date":1778139082476,"name":"королева","notes":"","phone":"+79287736353","total_orders":1,"total_spent":440.0,"updated_at":1778139082476},{"addresses":[],"bonus_balance":11.0,"created_at":1778138246770,"id":"CLIENT-71","last_order_date":1778138246806,"name":"усзн","notes":"","phone":"+79013881148","total_orders":1,"total_spent":220.0,"updated_at":1778138246806},{"addresses":[],"bonus_balance":22.5,"created_at":1778138188380,"id":"CLIENT-70","last_order_date":1778138188400,"name":"Гастелло","notes":"","phone":"+79515017409","total_orders":1,"total_spent":450.0,"updated_at":1778138188400}],"device_id":"android-4008934c-c970-4c15-afac-2258b550b451","manager_pin":"1010","timestamp":1778147700952,"version":1}