{"clients":[{"addresses":[{"address_text":"Сальск Станиславского 184","apartment":"","created_at":1779086583981,"house":"","id":"ADDR-114","is_default":false,"label":"","latitude":46.4706303,"longitude":41.5616845,"street":"Сальск Станиславского 184","updated_at":1779086583981}],"bonus_balance":11.5,"created_at":1779086583975,"id":"CLIENT-174","last_order_date":1779086584010,"name":"салон красоты","notes":"","phone":"+79809132004","total_orders":1,"total_spent":230.0,"updated_at":1779086584010}],"device_id":"android-4008934c-c970-4c15-afac-2258b550b451","manager_pin":"1010","timestamp":1779086825621,"version":1}