{"device_id":"android-4008934c-c970-4c15-afac-2258b550b451","manager_pin":"1010","orders":[{"address_id":"ADDR-126","address_latitude":46.462313,"address_longitude":41.5556002,"address_text":"Сальск Чернышевского 57","bonus_earned":11.0,"bonus_used":0.0,"client_id":"CLIENT-187","client_name":"Чернышевского","client_phone":"+79895200979","comment":"","created_at":1779170109739,"delivery_date":1779170070037,"delivery_time_slot":"","events":[],"id":"ORD-236-android-4008934c-c970-4c15-afac-2258b550b451","items":[{"price_at_moment":220.0,"product_id":"PROD-null","product_name":"Царица Гор вода 19 л","quantity":1.0,"sum":220.0}],"order_number":"ORD-20260519-162881","payment_status":"UNPAID","payment_type":"CASH","status":"NEW","sync_status":"NOT_SYNCED","total_amount":220.0,"updated_at":1779170109739},{"address_id":"ADDR-125","address_latitude":46.4749665,"address_longitude":41.5236393,"address_text":"Сальск Запорожская 3","bonus_earned":33.75,"bonus_used":0.0,"client_id":"CLIENT-186","client_name":"запорожская","client_phone":"+79286065808","comment":"","created_at":1779170060121,"delivery_date":1779170025097,"delivery_time_slot":"","events":[],"id":"ORD-235-android-4008934c-c970-4c15-afac-2258b550b451","items":[{"price_at_moment":225.0,"product_id":"PROD-null","product_name":"Жемчужина кавказа 19л","quantity":3.0,"sum":675.0}],"order_number":"ORD-20260519-476949","payment_status":"UNPAID","payment_type":"CASH","status":"IN_PROGRESS","sync_status":"NOT_SYNCED","total_amount":675.0,"updated_at":1779170119281}],"timestamp":1779170122102,"version":1}